abx_plugin_wget/__init__.py
abx_plugin_wget/binaries.py
abx_plugin_wget/config.py
abx_plugin_wget/extractors.py
abx_plugin_wget/wget.py
abx_plugin_wget/wget_util.py
abx_plugin_wget-2024.10.28.dist-info/METADATA
abx_plugin_wget-2024.10.28.dist-info/WHEEL
abx_plugin_wget-2024.10.28.dist-info/entry_points.txt
abx_plugin_wget-2024.10.28.dist-info/RECORD
